remittance/__init__.py
remittance/ais_invoice.py
remittance/conversion.py
remittance/debit_note.py
remittance/invoice.py
remittance/metadata.py
remittance/remittance.py
remittance/remittance_doc.py
remittance/utilities.py
remittance/utils.py
remittance/ais/__init__.py
remittance/ais/ais.py
remittance/ais/parser.py
remittance/ais/sage_import.py
remittance-0.0.47.dist-info/DESCRIPTION.rst
remittance-0.0.47.dist-info/METADATA
remittance-0.0.47.dist-info/RECORD
remittance-0.0.47.dist-info/WHEEL
remittance-0.0.47.dist-info/metadata.json
remittance-0.0.47.dist-info/top_level.txt
