Metadata-Version: 2.0
Name: remittance
Version: 0.0.47
Summary: A framework to model remittances.  Useful for writing software to process remittances.
Home-page: https://github.com/drummonds/remittance
Author: Humphrey Drummond
Author-email: hum3@drummond.info
License: MIT license
Keywords: remittance
Platform: UNKNOWN
Classifier: Development Status :: 4 - Beta
Classifier: Environment :: Console
Classifier: Intended Audience :: Developers
Classifier: Intended Audience :: Financial and Insurance Industry
Classifier: License :: OSI Approved :: MIT License
Classifier: Natural Language :: English
Classifier: Operating System :: OS Independent
Classifier: Programming Language :: Python :: 3.5
Classifier: Topic :: Office/Business
Classifier: Topic :: Office/Business :: Financial
Classifier: Topic :: Office/Business :: Financial :: Accounting
Classifier: Topic :: Software Development :: Libraries :: Python Modules
